README.md
setup.py
as_easy_as_pie/__init__.py
as_easy_as_pie/as_easy_as_pie.py
as_easy_as_pie/test_as_easy_as_pie.py
as_easy_as_pie.egg-info/PKG-INFO
as_easy_as_pie.egg-info/SOURCES.txt
as_easy_as_pie.egg-info/dependency_links.txt
as_easy_as_pie.egg-info/requires.txt
as_easy_as_pie.egg-info/top_level.txt