Metadata-Version: 2.1
Name: as-easy-as-pie
Version: 0.51
Summary: Really easy
Home-page: https://github.com/Pfython/as_easy_as_pie
Author: Peter
Author-email: peter@gmail.com
License: The Unlicense
Download-URL: https://github.com/Pfython/as_easy_as_pie/archive/0.51.tar.gz
Keywords: as_easy_as_pie,Peter,Pfython,
Platform: UNKNOWN
Classifier: Development Status :: 7 - Inactive
Classifier: Intended Audience :: Developers
Classifier: Operating System :: OS Independent
Classifier: Programming Language :: Python :: 3.6
Classifier: Programming Language :: Python :: 3.7
Classifier: Programming Language :: Python :: 3.8
Classifier: Programming Language :: Python :: 3.9
Classifier: Topic :: Communications :: Chat :: ICQ
Classifier: License :: OSI Approved :: The Unlicense (Unlicense)
